git_release/__init__.py
git_release/__main__.py
git_release/git_release.py
git_release-0.2.1.dist-info/LICENSE.txt
git_release-0.2.1.dist-info/METADATA
git_release-0.2.1.dist-info/WHEEL
git_release-0.2.1.dist-info/entry_points.txt
git_release-0.2.1.dist-info/top_level.txt
git_release-0.2.1.dist-info/RECORD
