Metadata-Version: 2.1
Name: git-release
Version: 0.2.1
Summary: Easily create releases in git
Home-page: https://github.com/iwishiwasaneagle/git-release/
Author: iwishiwasaneagle
Author-email: jh.ewers@gmail.com
License: GPL-3.0-or-later
Project-URL: Source, https://github.com/iwishiwasaneagle/git-release/
Platform: Linux
Classifier: Development Status :: 3 - Alpha
Classifier: Programming Language :: Python :: 3.8
Classifier: Programming Language :: Python :: 3.9
Classifier: Programming Language :: Python :: 3.10
Classifier: License :: OSI Approved :: GNU General Public License v3 or later (GPLv3+)
Classifier: Natural Language :: English
Classifier: Operating System :: Unix
Requires-Python: >=3.8
License-File: LICENSE.txt
Requires-Dist: loguru
Requires-Dist: gitpython
Requires-Dist: importlib-metadata ; python_version < "3.8"
Provides-Extra: test
Requires-Dist: setuptools ; extra == 'test'
Requires-Dist: pytest ; extra == 'test'
Requires-Dist: pytest-cov ; extra == 'test'
Requires-Dist: tox ; extra == 'test'
